{
  "collectionName": "components_fish_saltwaters",
  "info": {
    "displayName": "Saltwater",
    "description": ""
  },
  "options": {},
  "attributes": {
    "Fish": {
      "displayName": "Fish",
      "type": "component",
      "repeatable": false,
      "component": "saltwater.fish"
    },
    "Corals": {
      "displayName": "Corals",
      "type": "component",
      "repeatable": false,
      "component": "saltwater.corals"
    },
    "Crustaceans": {
      "displayName": "Crustaceans",
      "type": "component",
      "repeatable": false,
      "component": "saltwater.crustaceans"
    },
    "Mollusca": {
      "displayName": "Mollusca",
      "type": "component",
      "repeatable": false,
      "component": "saltwater.mollusca"
    },
    "Echinoderm": {
      "displayName": "Echinoderm",
      "type": "component",
      "repeatable": false,
      "component": "saltwater.echinoderm"
    }
  }
}
